setuptools_behave.py
behavecrackle/__init__.py
behavecrackle/__main__.py
behavecrackle/_stepimport.py
behavecrackle/_types.py
behavecrackle/capture.py
behavecrackle/configuration.py
behavecrackle/exception.py
behavecrackle/fixture.py
behavecrackle/i18n.py
behavecrackle/importer.py
behavecrackle/json_parser.py
behavecrackle/log_capture.py
behavecrackle/matchers.py
behavecrackle/model.py
behavecrackle/model_core.py
behavecrackle/model_describe.py
behavecrackle/parser.py
behavecrackle/python_feature.py
behavecrackle/runner.py
behavecrackle/runner_plugin.py
behavecrackle/runner_util.py
behavecrackle/step_registry.py
behavecrackle/tag_matcher.py
behavecrackle/textutil.py
behavecrackle/userdata.py
behavecrackle/version.py
behavecrackle/active_tag/__init__.py
behavecrackle/active_tag/python.py
behavecrackle/active_tag/python_feature.py
behavecrackle/api/__init__.py
behavecrackle/api/async_step.py
behavecrackle/api/runner.py
behavecrackle/api/runtime_constraint.py
behavecrackle/attic/__init__.py
behavecrackle/attic/tag_matcher.py
behavecrackle/compat/__init__.py
behavecrackle/compat/collections.py
behavecrackle/compat/exceptions.py
behavecrackle/contrib/__init__.py
behavecrackle/contrib/formatter_missing_steps.py
behavecrackle/contrib/scenario_autoretry.py
behavecrackle/contrib/substep_dirs.py
behavecrackle/formatter/__init__.py
behavecrackle/formatter/_builtins.py
behavecrackle/formatter/_registry.py
behavecrackle/formatter/ansi_escapes.py
behavecrackle/formatter/base.py
behavecrackle/formatter/formatters.py
behavecrackle/formatter/json.py
behavecrackle/formatter/null.py
behavecrackle/formatter/plain.py
behavecrackle/formatter/pretty.py
behavecrackle/formatter/progress.py
behavecrackle/formatter/rerun.py
behavecrackle/formatter/sphinx_steps.py
behavecrackle/formatter/sphinx_util.py
behavecrackle/formatter/steps.py
behavecrackle/formatter/tags.py
behavecrackle/reporter/__init__.py
behavecrackle/reporter/base.py
behavecrackle/reporter/junit.py
behavecrackle-1.2.6.2.dist-info/LICENSE
behavecrackle-1.2.6.2.dist-info/METADATA
behavecrackle-1.2.6.2.dist-info/WHEEL
behavecrackle-1.2.6.2.dist-info/entry_points.txt
behavecrackle-1.2.6.2.dist-info/top_level.txt
behavecrackle-1.2.6.2.dist-info/zip-safe
behavecrackle-1.2.6.2.dist-info/RECORD
